hepscale/__init__.py
hepscale/main.py
hepscale/plotting.py
hepscale/utility.py
hepscale-1.0.3.dist-info/LICENSE
hepscale-1.0.3.dist-info/METADATA
hepscale-1.0.3.dist-info/WHEEL
hepscale-1.0.3.dist-info/entry_points.txt
hepscale-1.0.3.dist-info/top_level.txt
hepscale-1.0.3.dist-info/RECORD
